ltq/__init__.py
ltq/app.py
ltq/cli.py
ltq/errors.py
ltq/logger.py
ltq/message.py
ltq/middleware.py
ltq/q.py
ltq/scheduler.py
ltq/task.py
ltq/utils.py
ltq/worker.py
ltq-0.3.1.dist-info/WHEEL
ltq-0.3.1.dist-info/entry_points.txt
ltq-0.3.1.dist-info/METADATA
ltq-0.3.1.dist-info/RECORD
