Metadata-Version: 2.3
Name: ltq
Version: 0.3.1
Summary: Add your description here
Author: Tom Clesius
Author-email: Tom Clesius <tomclesius@gmail.com>
Requires-Dist: redis>=7.1.0
Requires-Dist: croniter>=6.0.0 ; extra == 'scheduler'
Requires-Dist: sentry-sdk>=2.0.0 ; extra == 'sentry'
Requires-Python: >=3.13
Provides-Extra: scheduler
Provides-Extra: sentry
